package/__init__.py
package/matrix_game.py
tests/__init__.py
tests/test.py
antagonistic_game_solver-0.1.dist-info/LICENSE.txt.txt
antagonistic_game_solver-0.1.dist-info/METADATA
antagonistic_game_solver-0.1.dist-info/WHEEL
antagonistic_game_solver-0.1.dist-info/top_level.txt
antagonistic_game_solver-0.1.dist-info/RECORD
