Metadata-Version: 2.1
Name: antagonistic-game-solver
Version: 0.1
Home-page: https://github.com/oscar-foxtrot/antagonistic_game_solver
Author: Fostenko O.A.| Buzin N.I., CMC MSU
Author-email: oleg.fostenko.03@gmail.com
License: MIT
Project-URL: Author (Fostenko O.A.), https://vk.com/av1at0r
Project-URL: Author (Buzin N.I.), https://vk.com/buzin93
Project-URL: Source Code, https://github.com/oscar-foxtrot/antagonistic_game_solver
License-File: LICENSE.txt.txt
Requires-Dist: numpy >=1.26.1
Requires-Dist: sciPy >=1.11.3
